{
  "routes": [
    {
      "method": "GET",
      "path": "/product-descriptions",
      "handler": "product-description.find",
      "config": {
        "policies": []
      }
    },
    {
      "method": "GET",
      "path": "/product-descriptions/count",
      "handler": "product-description.count",
      "config": {
        "policies": []
      }
    },
    {
      "method": "GET",
      "path": "/product-descriptions/:id",
      "handler": "product-description.findOne",
      "config": {
        "policies": []
      }
    },
    {
      "method": "POST",
      "path": "/product-descriptions",
      "handler": "product-description.create",
      "config": {
        "policies": []
      }
    },
    {
      "method": "PUT",
      "path": "/product-descriptions/:id",
      "handler": "product-description.update",
      "config": {
        "policies": []
      }
    },
    {
      "method": "DELETE",
      "path": "/product-descriptions/:id",
      "handler": "product-description.delete",
      "config": {
        "policies": []
      }
    }
  ]
}
